pyunit_idcard/__init__.py
pyunit_idcard/idCard.json
pyunit_idcard/idcard.py
pyunit_idcard-2020.6.22.dist-info/LICENSE
pyunit_idcard-2020.6.22.dist-info/METADATA
pyunit_idcard-2020.6.22.dist-info/WHEEL
pyunit_idcard-2020.6.22.dist-info/top_level.txt
pyunit_idcard-2020.6.22.dist-info/RECORD
