Metadata-Version: 2.1
Name: pyunit-idcard
Version: 2020.6.22
Summary: 身份证实体抽取，身份证补全，身份证检测等功能。
Home-page: https://github.com/PyUnit/pyunit-idCard
Author: Jtyoui
Author-email: jtyoui@qq.com
License: MIT Licence
Platform: any
Classifier: Programming Language :: Python :: 3
Classifier: License :: OSI Approved :: MIT License
Classifier: Operating System :: OS Independent
